statfenics/__init__.py
statfenics/covariance.py
statfenics/utils.py
statfenics-0.0.1.dist-info/METADATA
statfenics-0.0.1.dist-info/WHEEL
statfenics-0.0.1.dist-info/licenses/LICENSE
statfenics-0.0.1.dist-info/RECORD
