Metadata-Version: 2.1
Name: statfenics
Version: 0.0.1
Summary: Tools for statFEM problems with Fenics
Project-URL: Homepage, https://github.com/connor-duffin/statfenics
Project-URL: Bug Tracker, https://github.com/connor-duffin/statfenics/issues
Author-email: Connor Duffin <cpd32@cam.ac.uk>
License: Copyright (c) 2021 Connor Duffin
Classifier: License :: OSI Approved :: MIT License
Classifier: Operating System :: OS Independent
Classifier: Programming Language :: Python :: 3
Requires-Python: >=3.7
